[
  {
    "BCA": {
      "01.01.2020": {
        "preorder": "0",
        "sum": "2"
      },
      "01.01.2020": {
        "preorder": "0",
        "sum": "2"
      },
      "01.01.2020": {
        "preorder": "0",
        "sum": "2"
      },
      "01.01.2020": {
        "preorder": "0",
        "sum": "2"
      },
      "01.01.2020": {
        "preorder": "0",
        "sum": "2"
      }
    },
    "509": {
      "01.01.2020": {
        "preorder": "0",
        "sum": "2"
      },
      "01.01.2020": {
        "preorder": "0",
        "sum": "2"
      },
      "01.01.2020": {
        "preorder": "0",
        "sum": "2"
      },
      "01.01.2020": {
        "preorder": "0",
        "sum": "2"
      },
      "01.01.2020": {
        "preorder": "0",
        "sum": "2"
      }
    },
  }
]
